Metadata-Version: 2.1
Name: PythonChef
Version: 0.4.0
Summary: Python implementation of a Chef API client.
Home-page: http://github.com/elvinup/pychef
Author: Noah Kantrowitz
Author-email: noah@coderanger.net
License: Apache 2.0
Classifier: Development Status :: 5 - Production/Stable
Classifier: License :: OSI Approved :: Apache Software License
Classifier: Natural Language :: English
Classifier: Operating System :: OS Independent
Classifier: Programming Language :: Python
License-File: LICENSE
